tests/__init__.py
tests/algebra/__init__.py
tests/algebra/test_algebra.py
tests/algebra/edo/__init__.py
tests/algebra/edo/test_edo.py
tests/algebra/integral/__init__.py
tests/algebra/integral/test_integral_double.py
tests/algebra/integral/test_integral_simple.py
tests/algebra/roots/__init__.py
tests/algebra/roots/test_roots.py
tests/interpolation/__init__.py
tests/interpolation/test_interpolation.py
yoshi_otter/__init__.py
yoshi_otter/algebra/__algebra.py
yoshi_otter/algebra/__init__.py
yoshi_otter/algebra/edo/__edo.py
yoshi_otter/algebra/edo/__init__.py
yoshi_otter/algebra/integral/__init__.py
yoshi_otter/algebra/integral/double.py
yoshi_otter/algebra/integral/simple.py
yoshi_otter/algebra/roots/__init__.py
yoshi_otter/algebra/roots/__roots.py
yoshi_otter/interpolation/__init__.py
yoshi_otter/interpolation/__interpolation.py
yoshi_otter/shared/__init__.py
yoshi_otter/shared/invalid_function_signature.py
yoshi_otter-2.0.3692104139.dist-info/LICENSE
yoshi_otter-2.0.3692104139.dist-info/METADATA
yoshi_otter-2.0.3692104139.dist-info/WHEEL
yoshi_otter-2.0.3692104139.dist-info/top_level.txt
yoshi_otter-2.0.3692104139.dist-info/RECORD
