Metadata-Version: 2.1
Name: yoshi-otter
Version: 2.0.3692104139
Summary: Numeric Calculus python module in the topic of Algebra Functions
Home-page: https://github.com/HideyoshiNakazone/Otter-NumericCalculus.git
Author: Vitor Hideyoshi
Author-email: vitor.h.n.batista@gmail.com
Classifier: Programming Language :: Python :: 3
Classifier: License :: OSI Approved :: GNU General Public License v2 (GPLv2)
Classifier: Operating System :: OS Independent
Classifier: Development Status :: 2 - Pre-Alpha
Requires-Python: >=3.8
License-File: LICENSE
Requires-Dist: numpy
Requires-Dist: pandas
Requires-Dist: yoshi-seals
